README.md
setup.py
pytgbot/__init__.py
pytgbot/exceptions.py
pytgbot/webhook.py
pytgbot.egg-info/PKG-INFO
pytgbot.egg-info/SOURCES.txt
pytgbot.egg-info/dependency_links.txt
pytgbot.egg-info/requires.txt
pytgbot.egg-info/top_level.txt
pytgbot/api_types/__init__.py
pytgbot/api_types/receivable/__init__.py
pytgbot/api_types/receivable/game.py
pytgbot/api_types/receivable/inline.py
pytgbot/api_types/receivable/media.py
pytgbot/api_types/receivable/passport.py
pytgbot/api_types/receivable/payments.py
pytgbot/api_types/receivable/peer.py
pytgbot/api_types/receivable/responses.py
pytgbot/api_types/receivable/service.py
pytgbot/api_types/receivable/stickers.py
pytgbot/api_types/receivable/updates.py
pytgbot/api_types/sendable/__init__.py
pytgbot/api_types/sendable/command.py
pytgbot/api_types/sendable/files.py
pytgbot/api_types/sendable/inline.py
pytgbot/api_types/sendable/input_media.py
pytgbot/api_types/sendable/passport.py
pytgbot/api_types/sendable/payments.py
pytgbot/api_types/sendable/reply_markup.py
pytgbot/bot/__init__.py
pytgbot/bot/asynchronous.py
pytgbot/bot/base.py
pytgbot/bot/synchronous.py