Metadata-Version: 2.1
Name: pytgbot
Version: 5.7
Summary: Connect to the Telegram Bot API, receive and send Telegram messages.
Home-page: https://github.com/luckydonald/pytgbot
Author: luckydonald
Author-email: code@luckydonald.de
License: MIT
Keywords: telegram bot api python message send receive python secure fast answer reply image voice picture location contacts typing multi messanger inline quick reply gif image video mp4 mpeg4 sticker file_id markdown markdownV2
Platform: UNKNOWN
Classifier: Development Status :: 4 - Beta
Classifier: Intended Audience :: Developers
Classifier: Topic :: Communications
Classifier: Topic :: Communications :: Chat
Classifier: Topic :: Multimedia
Classifier: Topic :: Software Development :: Libraries
Classifier: Topic :: Software Development :: Libraries :: Python Modules
Classifier: License :: OSI Approved :: GNU General Public License v3 or later (GPLv3+)
Classifier: Programming Language :: Python :: 2.7
Classifier: Programming Language :: Python :: 3
Classifier: Programming Language :: Python :: 3.4
Classifier: Operating System :: MacOS :: MacOS X
Classifier: Operating System :: Unix
Provides-Extra: async
Provides-Extra: dev
Provides-Extra: sync
